rice_vpaa/__init__.py
rice_vpaa/client.py
rice_vpaa/config.py
rice_vpaa/models.py
rice_vpaa/auth/client.py
rice_vpaa/auth/models.py
rice_vpaa/data_lagoon/__init__.py
rice_vpaa/data_lagoon/data_lagoon.py
rice_vpaa_sdk-0.1.8.dist-info/METADATA
rice_vpaa_sdk-0.1.8.dist-info/WHEEL
rice_vpaa_sdk-0.1.8.dist-info/top_level.txt
rice_vpaa_sdk-0.1.8.dist-info/RECORD
