Metadata-Version: 2.2
Name: rice-vpaa-sdk
Version: 0.1.8
Summary: SDK for the Rice VPAA API
Author-email: Cody VanZandt <cav3@rice.edu>
Project-URL: Homepage, https://github.com/Rice-University-Academic-Affairs/VPAA-API
Classifier: Programming Language :: Python :: 3
Classifier: License :: OSI Approved :: MIT License
Classifier: Operating System :: OS Independent
Requires-Python: >=3.10
Requires-Dist: pydantic>=2.0.0
Requires-Dist: requests>=2.0.0
Requires-Dist: boto3>=1.36.0
Requires-Dist: pyarrow>=19.0.0
Requires-Dist: pandas>=2.2.0
Requires-Dist: duckdb>=1.2.0
